fast_fhir/__init__.py
fast_fhir/all_resources.py
fast_fhir/datatypes.py
fast_fhir/fast_parser.py
fast_fhir/fhir_clinical_c.py
fast_fhir/fhir_datatypes_c.cpython-313-darwin.so
fast_fhir/fhir_datatypes_c.py
fast_fhir/fhir_financial_c.py
fast_fhir/fhir_foundation_c.cpython-313-darwin.so
fast_fhir/fhir_foundation_c.py
fast_fhir/fhir_medication_c.py
fast_fhir/fhir_parser_c.cpython-313-darwin.so
fast_fhir/fhir_parser_c.py
fast_fhir/fhir_specialized_c.py
fast_fhir/fhir_workflow_c.py
fast_fhir/foundation.py
fast_fhir/parser.py
fast_fhir/terminology.py
fast_fhir/deserializers/__init__.py
fast_fhir/deserializers/deserializers.py
fast_fhir/deserializers/entities_deserializers.py
fast_fhir/deserializers/foundation_deserializers.py
fast_fhir/deserializers/pydantic_care_provision.py
fast_fhir/deserializers/pydantic_entities.py
fast_fhir/deserializers/pydantic_foundation.py
fast_fhir/deserializers/pydantic_models.py
fast_fhir/ext/fhir_all_resources.h
fast_fhir/ext/fhir_clinical.h
fast_fhir/ext/fhir_datatypes.c
fast_fhir/ext/fhir_datatypes.h
fast_fhir/ext/fhir_datatypes_python.c
fast_fhir/ext/fhir_financial.h
fast_fhir/ext/fhir_foundation.c
fast_fhir/ext/fhir_foundation.h
fast_fhir/ext/fhir_foundation_python.c
fast_fhir/ext/fhir_medication.h
fast_fhir/ext/fhir_new_resources.c
fast_fhir/ext/fhir_new_resources_python.c
fast_fhir/ext/fhir_parser.c
fast_fhir/ext/fhir_specialized.h
fast_fhir/ext/fhir_workflow.h
fast_fhir/ext/common/fhir_common.c
fast_fhir/ext/common/fhir_common.h
fast_fhir/ext/common/fhir_resource_base.c
fast_fhir/ext/common/fhir_resource_base.h
fast_fhir/ext/resources/fhir_biologically_derived_product.h
fast_fhir/ext/resources/fhir_careplan.c
fast_fhir/ext/resources/fhir_careplan.h
fast_fhir/ext/resources/fhir_careteam.h
fast_fhir/ext/resources/fhir_device_metric.c
fast_fhir/ext/resources/fhir_device_metric.h
fast_fhir/ext/resources/fhir_encounter.c
fast_fhir/ext/resources/fhir_encounter.h
fast_fhir/ext/resources/fhir_goal.h
fast_fhir/ext/resources/fhir_location.c
fhir_fast_parser-0.1.0.dist-info/licenses/LICENSE
fhir_fast_parser-0.1.0.dist-info/METADATA
fhir_fast_parser-0.1.0.dist-info/WHEEL
fhir_fast_parser-0.1.0.dist-info/top_level.txt
fhir_fast_parser-0.1.0.dist-info/RECORD
