Metadata-Version: 2.4
Name: fhir-fast-parser
Version: 0.1.0
Summary: High-performance FHIR R5 parser and validator for SMART on FHIR applications - Fast JSON deserialization with Pydantic validation for healthcare interoperability
Author-email: Archit Kapoor <archit47@users.noreply.github.com>
Maintainer-email: Archit Kapoor <archit47@users.noreply.github.com>
License: MIT
Project-URL: Homepage, https://github.com/archit47/fast-fhir
Project-URL: Repository, https://github.com/archit47/fast-fhir
Project-URL: Documentation, https://github.com/archit47/fast-fhir#readme
Project-URL: Bug Tracker, https://github.com/archit47/fast-fhir/issues
Project-URL: Benchmarks, https://github.com/archit47/fast-fhir/blob/master/benchmarks/COMPARATIVE_RESULTS.md
Project-URL: Examples, https://github.com/archit47/fast-fhir/tree/master/examples
Project-URL: FHIR R5 Specification, https://hl7.org/fhir/R5/
Project-URL: SMART on FHIR, https://smarthealthit.org/
Keywords: fhir,fhir-r5,smart-on-fhir,parser,healthcare,hl7,json,performance,fast,c-extensions,medical,interoperability,validation,deserializer,ehr,epic,cerner,allscripts,clinical-data,patient-data,healthcare-integration,fhir-client,fhir-server,healthcare-api,medical-records,health-informatics
Classifier: Development Status :: 5 - Production/Stable
Classifier: Intended Audience :: Developers
Classifier: Intended Audience :: Healthcare Industry
Classifier: Intended Audience :: Information Technology
Classifier: Operating System :: OS Independent
Classifier: Operating System :: POSIX :: Linux
Classifier: Operating System :: MacOS
Classifier: Operating System :: Microsoft :: Windows
Classifier: Programming Language :: Python :: 3
Classifier: Programming Language :: Python :: 3.8
Classifier: Programming Language :: Python :: 3.9
Classifier: Programming Language :: Python :: 3.10
Classifier: Programming Language :: Python :: 3.11
Classifier: Programming Language :: Python :: 3.12
Classifier: Programming Language :: Python :: Implementation :: CPython
Classifier: Programming Language :: C
Classifier: Topic :: Software Development :: Libraries :: Python Modules
Classifier: Topic :: Scientific/Engineering :: Medical Science Apps.
Classifier: Topic :: Internet :: WWW/HTTP :: Dynamic Content
Classifier: Topic :: Database :: Front-Ends
Classifier: Topic :: System :: Archiving :: Packaging
Classifier: Topic :: Text Processing :: Markup
Classifier: Environment :: Web Environment
Classifier: Framework :: FastAPI
Classifier: Framework :: Django
Classifier: Framework :: Flask
Classifier: Natural Language :: English
Classifier: Typing :: Typed
Requires-Python: >=3.8
License-File: LICENSE
Requires-Dist: pkgconfig>=1.5.0
Requires-Dist: pydantic>=1.8.0
Provides-Extra: dev
Requires-Dist: pytest>=7.0.0; extra == "dev"
Requires-Dist: black>=22.0.0; extra == "dev"
Requires-Dist: flake8>=4.0.0; extra == "dev"
Requires-Dist: mypy>=0.950; extra == "dev"
Requires-Dist: build>=0.8.0; extra == "dev"
Requires-Dist: twine>=4.0.0; extra == "dev"
Provides-Extra: benchmarks
Requires-Dist: pytest>=7.0.0; extra == "benchmarks"
Requires-Dist: fhir.resources>=8.0.0; extra == "benchmarks"
Provides-Extra: validation
Requires-Dist: pydantic>=1.8.0; extra == "validation"
Provides-Extra: smart-on-fhir
Requires-Dist: requests>=2.25.0; extra == "smart-on-fhir"
Requires-Dist: httpx>=0.20.0; extra == "smart-on-fhir"
Provides-Extra: all
Requires-Dist: pytest>=7.0.0; extra == "all"
Requires-Dist: fhir.resources>=8.0.0; extra == "all"
Requires-Dist: pydantic>=1.8.0; extra == "all"
Requires-Dist: requests>=2.25.0; extra == "all"
Requires-Dist: httpx>=0.20.0; extra == "all"
Dynamic: license-file
